mpi4pyd/__init__.py
mpi4pyd/__version__.py
mpi4pyd/dummyMPI.py
mpi4pyd/utils.py
mpi4pyd/MPI/__init__.py
mpi4pyd/MPI/_helpers.py
mpi4pyd/MPI/_hybrid_comm.py
mpi4pyd/MPI/tests/__init__.py
mpi4pyd/MPI/tests/test_MPI.py
mpi4pyd/tests/__init__.py
mpi4pyd/tests/test_dummyMPI.py
mpi4pyd/tests/test_utils.py
mpi4pyd-0.3.1.dist-info/LICENSE
mpi4pyd-0.3.1.dist-info/METADATA
mpi4pyd-0.3.1.dist-info/WHEEL
mpi4pyd-0.3.1.dist-info/top_level.txt
mpi4pyd-0.3.1.dist-info/RECORD
