Metadata-Version: 2.1
Name: mpi4pyd
Version: 0.3.1
Summary: mpi4pyd: MPI for Python Dummies
Home-page: https://github.com/1313e/mpi4pyd
Author: Ellert van der Velden
Author-email: ellert_vandervelden@outlook.com
Maintainer: 1313e
License: BSD-3
Keywords: mpi4pyd
Platform: Windows
Platform: Mac OS-X
Platform: Linux
Platform: Unix
Classifier: Development Status :: 3 - Alpha
Classifier: Intended Audience :: Developers
Classifier: License :: OSI Approved :: BSD License
Classifier: Natural Language :: English
Classifier: Operating System :: MacOS
Classifier: Operating System :: Microsoft :: Windows
Classifier: Operating System :: Unix
Classifier: Programming Language :: Python
Classifier: Programming Language :: Python :: 3
Classifier: Programming Language :: Python :: 3.5
Classifier: Programming Language :: Python :: 3.6
Classifier: Programming Language :: Python :: 3.7
Classifier: Programming Language :: Python :: 3.8
Classifier: Topic :: Software Development
Requires-Python: >=3.5, <4
Requires-Dist: e13tools (>=0.6.3)
Requires-Dist: numpy (>=1.12.0)
